awspstore/__init__.py
awspstore-1.4.3.dist-info/LICENSE
awspstore-1.4.3.dist-info/METADATA
awspstore-1.4.3.dist-info/WHEEL
awspstore-1.4.3.dist-info/top_level.txt
awspstore-1.4.3.dist-info/RECORD
