Metadata-Version: 2.1
Name: awspstore
Version: 1.4.3
Summary: Vault for your software project using AWS Parameter Store
Home-page: https://github.com/eldad1221/aws-vault
Author: Eldad Bishari
Author-email: eldad@1221tlv.org
Classifier: Programming Language :: Python :: 3
Classifier: License :: OSI Approved :: MIT License
Classifier: Operating System :: OS Independent
Requires-Python: >=3.7
License-File: LICENSE
Requires-Dist: boto3 >=1.26.3
Requires-Dist: quickbelog >=1.1.0
